msu_test_video_creator/__init__.py
msu_test_video_creator/__main__.py
msu_test_video_creator/version.py
msu_test_video_creator/video_creator.py
msu_test_video_creator-0.2.0.dist-info/LICENSE
msu_test_video_creator-0.2.0.dist-info/METADATA
msu_test_video_creator-0.2.0.dist-info/WHEEL
msu_test_video_creator-0.2.0.dist-info/entry_points.txt
msu_test_video_creator-0.2.0.dist-info/RECORD
